plsxml/__init__.py
plsxml/plsxml.py
plsxml/plsxml_test.py
plsxml/data/__init__.py
plsxml/data/galloping.xml
plsxml/data/galloping.zip
plsxml/data/galloping_empty.xml
plsxml/data/loader.py
plsxml-1.2.0.dist-info/LICENSE
plsxml-1.2.0.dist-info/METADATA
plsxml-1.2.0.dist-info/WHEEL
plsxml-1.2.0.dist-info/top_level.txt
plsxml-1.2.0.dist-info/RECORD
