Metadata-Version: 2.1
Name: plsxml
Version: 1.2.0
Summary: Parse PLS-CADD XML files to dictionaries and data frames.
Author-email: Matt Pewsey <mattpewsey+pypi@gmail.com>
Project-URL: homepage, https://github.com/mpewsey/plsxml
Classifier: Programming Language :: Python :: 2.7
Classifier: Programming Language :: Python :: 3.5
Classifier: Programming Language :: Python :: 3.6
Classifier: Operating System :: OS Independent
Classifier: License :: OSI Approved :: BSD License
Requires-Python: !=3.0,!=3.1,!=3.2,!=3.3,!=3.4,>=2.7
License-File: LICENSE
Requires-Dist: pandas (>=0.23.0)
Provides-Extra: docs
Requires-Dist: docutils (==0.14) ; extra == 'docs'
Requires-Dist: numpydoc (>=0.8.0) ; extra == 'docs'
Provides-Extra: test
Requires-Dist: pytest (>=3.5.1) ; extra == 'test'
Requires-Dist: pytest-cov (>=2.5.1) ; extra == 'test'
Requires-Dist: codecov (>=2.0.15) ; extra == 'test'
